domicolor/CMakeLists.txt
domicolor/README.md
domicolor/__init__.py
domicolor/cpp/domicolor_backend.cpp
domicolor/pybind11/.appveyor.yml
domicolor/pybind11/.clang-tidy
domicolor/pybind11/.cmake-format.yaml
domicolor/pybind11/.github/CONTRIBUTING.md
domicolor/pybind11/.github/ISSUE_TEMPLATE/bug-report.md
domicolor/pybind11/.github/ISSUE_TEMPLATE/config.yml
domicolor/pybind11/.github/ISSUE_TEMPLATE/feature-request.md
domicolor/pybind11/.github/ISSUE_TEMPLATE/question.md
domicolor/pybind11/.github/workflows/ci.yml
domicolor/pybind11/.github/workflows/configure.yml
domicolor/pybind11/.github/workflows/format.yml
domicolor/pybind11/.gitignore
domicolor/pybind11/.pre-commit-config.yaml
domicolor/pybind11/.readthedocs.yml
domicolor/pybind11/CMakeLists.txt
domicolor/pybind11/LICENSE
domicolor/pybind11/MANIFEST.in
domicolor/pybind11/README.md
domicolor/pybind11/docs/Doxyfile
domicolor/pybind11/docs/_static/theme_overrides.css
domicolor/pybind11/docs/advanced/cast/chrono.rst
domicolor/pybind11/docs/advanced/cast/custom.rst
domicolor/pybind11/docs/advanced/cast/eigen.rst
domicolor/pybind11/docs/advanced/cast/functional.rst
domicolor/pybind11/docs/advanced/cast/index.rst
domicolor/pybind11/docs/advanced/cast/overview.rst
domicolor/pybind11/docs/advanced/cast/stl.rst
domicolor/pybind11/docs/advanced/cast/strings.rst
domicolor/pybind11/docs/advanced/classes.rst
domicolor/pybind11/docs/advanced/embedding.rst
domicolor/pybind11/docs/advanced/exceptions.rst
domicolor/pybind11/docs/advanced/functions.rst
domicolor/pybind11/docs/advanced/misc.rst
domicolor/pybind11/docs/advanced/pycpp/index.rst
domicolor/pybind11/docs/advanced/pycpp/numpy.rst
domicolor/pybind11/docs/advanced/pycpp/object.rst
domicolor/pybind11/docs/advanced/pycpp/utilities.rst
domicolor/pybind11/docs/advanced/smart_ptrs.rst
domicolor/pybind11/docs/basics.rst
domicolor/pybind11/docs/benchmark.py
domicolor/pybind11/docs/benchmark.rst
domicolor/pybind11/docs/changelog.rst
domicolor/pybind11/docs/classes.rst
domicolor-0.4.2.dist-info/entry_points.txt
domicolor-0.4.2.dist-info/LICENSE
domicolor-0.4.2.dist-info/LICENSE.rst
domicolor-0.4.2.dist-info/WHEEL
domicolor-0.4.2.dist-info/METADATA
domicolor-0.4.2.dist-info/RECORD
