Metadata-Version: 2.1
Name: domicolor
Version: 0.4.2
Summary: Fast dominant color extraction library
Home-page: https://github.com/DmitriyValetov/domicolor
Keywords: domicolor
Author: Dmitriy Valetov
Author-email: dmitriy.valetov@phystech.edu
Requires-Python: >=3.8,<3.10
Classifier: Development Status :: 2 - Pre-Alpha
Classifier: Intended Audience :: Developers
Classifier: License :: OSI Approved :: MIT License
Classifier: Natural Language :: English
Classifier: Programming Language :: Python :: 3
Classifier: Programming Language :: Python :: 3.8
Classifier: Programming Language :: Python :: 3.9
Requires-Dist: click (>=8.0.3,<9.0.0)
Requires-Dist: numpy (>=1.21.0,<2.0.0)
Requires-Dist: pillow (>=9.0.1,<10.0.0)
Project-URL: Bug Tracker, https://github.com/DmitriyValetov/domicolor/issues
Project-URL: Documentation, https://domicolor.readthedocs.io
Project-URL: Repository, https://github.com/DmitriyValetov/domicolor
